{
  "document_title": "Bathymetry 250K Scale",
  "document_id": "massgis:GISDATA.BTHOS250_POLY",
  "layer_id": "massgis:GISDATA.BTHOS250_POLY",
  "layer_type": "poly",
  "layer_date": "",
  "layer_description": "GeoServer layer: GISDATA.BTHOS250_POLY",
  "category": "Coastal and Marine Features",
  "subcategory": "Bathymetry",
  "source_type": "GeoServer",
  "document_type": "layer",
  "search_terms": [
    "bathymetry",
    "bathymetric map",
    "underwater topography",
    "sea floor",
    "depth contours",
    "marine depth",
    "coastal bathymetry",
    "ocean floor",
    "250k scale"
  ],
  "column_summary": "OBJECTID, DEPTH_NOS, DEPTHRANGE, SHAPE, SHAPE.AREA, SHAPE.LEN"
}