{
  "document_title": "DEP 2013 Tributaries thereto Watersheds",
  "document_id": "massgis:GISDATA.SWQS_2013_TRIBUTARY_AREA",
  "layer_id": "massgis:GISDATA.SWQS_2013_TRIBUTARY_AREA",
  "layer_type": "poly",
  "layer_date": "2013",
  "layer_description": "GeoServer layer: GISDATA.SWQS_2013_TRIBUTARY_AREA",
  "category": "Regulated Areas",
  "subcategory": "DEP Surface Water Quality Standards",
  "source_type": "GeoServer",
  "document_type": "layer",
  "search_terms": [
    "dep 2013 tributaries",
    "tributaries watersheds",
    "2013 tributary area",
    "surface water quality",
    "swqs tributary area",
    "water quality standards",
    "massgis tributaries",
    "watershed boundaries",
    "regulated areas",
    "geoserver layer"
  ],
  "column_summary": "OBJECTID, REG_DATE, REG_TABLE, REG_BASIN, WATERS, BOUNDARY, MILE_POINT, CLASS, QUALIFIER, SHAPE, SHAPE.AREA, SHAPE.LEN"
}